setup.py
tutu/Binomialdistribution.py
tutu/Gaussiandistribution.py
tutu/Generaldistribution.py
tutu/__init__.py
tutu.egg-info/PKG-INFO
tutu.egg-info/SOURCES.txt
tutu.egg-info/dependency_links.txt
tutu.egg-info/not-zip-safe
tutu.egg-info/top_level.txt