Metadata-Version: 1.0
Name: tutu
Version: 0.1
Summary: Gaussian distributions
Home-page: UNKNOWN
Author: Changyu (Steven) Lin
Author-email: changyu.lin2011@gmail.com
License: UNKNOWN
Platform: UNKNOWN
